<biblioteca>
  <directorios>
    <entry>
      <string>C:\hlocal\workspace-3.4.2\IS-2011\src\Recursos</string>
      <dir>
        <dirPath>C:\hlocal\workspace-3.4.2\IS-2011\src\Recursos</dirPath>
        <listaCanciones>
          <track>
            <trackPath>01 Maldita Nerea &amp; Los Delincuentes -  el secreto de las tortugas.mp3</trackPath>
            <titulo>01 el secreto de las tortugas</titulo>
            <album>Desconocido</album>
            <genero>Desconocido</genero>
            <artista>Desconocido</artista>
            <duracion>247</duracion>
          </track>
        </listaCanciones>
      </dir>
    </entry>
    <entry>
      <string>C:\hlocal\workspace-3.4.2\IS-2011\src\Recursos\canciones</string>
      <dir>
        <dirPath>C:\hlocal\workspace-3.4.2\IS-2011\src\Recursos\canciones</dirPath>
        <listaCanciones>
          <track>
            <trackPath>20.desakato-OctubresRotos.mp3</trackPath>
            <titulo>Octubres rotos</titulo>
            <album>Con el viento de cara</album>
            <genero>Punk-Rock_Fussion</genero>
            <artista>Desconocido</artista>
            <duracion>201</duracion>
          </track>
        </listaCanciones>
      </dir>
    </entry>
  </directorios>
</biblioteca>